cat_admin_tool/__init__.py
cat_admin_tool-9.1.0.dist-info/METADATA
cat_admin_tool-9.1.0.dist-info/WHEEL
cat_admin_tool-9.1.0.dist-info/top_level.txt
cat_admin_tool-9.1.0.dist-info/RECORD
